<?xml version="1.0" encoding="utf-8"?>
<root>
	<status>success</status>
	<message>The COMPARABILITY field for indicator 4-1-2, translated into all languages</message>
	<data>
		<languages>
			<language lang="en"> &lt;p&gt; The indicator &quot;Percentage of students recognized to complete primary school&quot; is one of Vietnam&apos;s indicators to reflect the global sustainable development target &quot;&lt;strong&gt; 4.1.1: &lt;/strong&gt; Proportion of children and young people: (a) in grades 2/3; (b) at the end of primary; and (c) at the end of lower secondary achieving at least a minimum proficiency level in (i) reading and (ii) mathematics, by sex” &lt;/p&gt;
 &lt;p&gt; However, the indicator does not guarantee global comparability because the content, scope and calculation method of Vietnam are not the same as the global standard. &lt;/p&gt;
			</language>
			<language lang="vi">&lt;p&gt;Chỉ tiêu “Tỷ lệ học sinh được công nhận hoàn thành chương trình tiểu học” là một trong những chỉ tiêu của Việt Nam để phản ánh cho chỉ tiêu phát triển bền vững toàn cầu “&lt;strong&gt;4.1.1:&lt;/strong&gt; Proportion of children and young people: (a) in grades 2/3; (b) at the end of primary; and (c) at the end of lower secondary achieving at least a minimum proficiency level in (i) reading and (ii) mathematics, by sex”&lt;/p&gt;
&lt;p&gt;Tuy nhiên chỉ tiêu không bảo đảm tính so sánh toàn cầu do nội dung, phạm vi, phương pháp tính toán của Việt Nam không giống chuẩn toàn cầu.&lt;/p&gt;
			</language>
</languages>
</data>
</root>
