{"status":"success","message":"The COMPARABILITY field for indicator 6-1-1, translated into all languages","data":{"en":" <p> The indicator “Proportion of urban population provided with clean water through centralized water supply system” is one of the indicators that partly reflects the global SDG target “6.1.1.Proportion of population using safely managed drinking” water services” </p>","vi":"<p>Chỉ tiêu “Tỷ lệ dân số đô thị được cung cấp nước sạch qua hệ thống cấp nước tập trung” là một trong những chỉ tiêu phản ánh 1 phần chỉ tiêu SDG toàn cầu “6.1.1.Proportion of population using safely managed drinking water services”</p>"}}