<?xml version="1.0" encoding="utf-8"?>
<root>
	<status>success</status>
	<message>The RATIONALE field for indicator 4-2-1, translated into all languages</message>
	<data>
		<languages>
			<language lang="en"/>
			<language lang="vi">&lt;p&gt;Phát triển của trẻ em dưới 5 tuổi là bước khởi đầu cho sự phát triển trong cả cuộc đời. Đầu tư cho phát triển của trẻ em dưới 5 tuổi là việc đầu tư quan trọng và hiệu quả nhất mà một quốc gia có thể thực hiện để cải thiện sức khoẻ, giáo dục và năng suất cho người trưởng thành nhằm xây dựng nguồn nhân lực và thúc đẩy phát triển bền vững. Đầu tư cho phát triển của trẻ em dưới 5 tuổi là chỉ tiêu tốt và hợp lý cho sự phát triển của đất nước.&lt;/p&gt;
			</language>
</languages>
</data>
</root>
