<?xml version="1.0" encoding="utf-8"?>
<root>
	<status>success</status>
	<message>The COVERAGE field for indicator 5-3-1, translated into all languages</message>
	<data>
		<languages>
			<language lang="en"> &lt;p&gt; - Data available for urban/rural subdivision; nation; region; province/city in 2019 &lt;/p&gt;
 &lt;p&gt; - 2010 and 2014 only have general data; No data available for subtypes &lt;/p&gt;
 &lt;p&gt; (Published source: MICS census (2011, 2014); Population and housing census 2019) &lt;/p&gt;
			</language>
			<language lang="vi">&lt;p&gt;- Số liệu có cho phân tổ thành thị/nông thôn; dân tộc; vùng; tỉnh/thành phố vào năm 2019 &lt;/p&gt;
&lt;p&gt;- Năm 2010 và 2014 chỉ có số liệu chung; không có số liệu cho các phân tổ&lt;/p&gt;
&lt;p&gt;(Nguồn công bố: Điều tra MICS (2011, 2014); Tổng điều tra dân số và nhà ở 2019)&lt;/p&gt;
			</language>
</languages>
</data>
</root>
